{
    "answer": "The increase in mandatory funding for VA benefit programs from FY2024 to FY2025 was $28.4 billion for Compensation and Pensions, $4.14 billion for Cost of War (including Toxic Exposures Fund), and no increase was reported for Housing and Insurance or Readjustment Benefits.",
    "ground_truth": "$41.8 billion or 21.6%",
    "rewards": [
        0,
        0,
        0,
        0,
        0,
        0,
        0,
        0
    ],
    "reward_sum": 0,
    "turns": 8,
    "search count": 7,
    "script count": 0,
    "summary count": 0,
    "context lengths": [
        866,
        2001,
        3266,
        4550,
        6171,
        7649,
        9248,
        11278
    ]
}