{
    "answer": "The image depicts quantitative data, likely in the section \"The Numbers\" where graphs and figures are commonly found in such market forecasts.",
    "ground_truth": "Photograph of an airplane in flight; no chart, graph, or quantitative data.",
    "rewards": [
        0,
        0,
        0,
        0,
        0,
        0
    ],
    "reward_sum": 0,
    "turns": 6,
    "search count": 4,
    "script count": 0,
    "summary count": 0,
    "context lengths": [
        812,
        1139,
        2464,
        3698,
        5649,
        6166
    ]
}