{
    "answer": "No unique article from the 2025 annual trends collection on researchworld.com can be identified by its content on the 2025 Trends page. Articles on the page typically mention \"2025 Trends\" as a general topic, but no single article is uniquely identified by its content on that specific page as per the search results.",
    "ground_truth": "Research World official website 2025 Trends article (2025 Trends)",
    "rewards": [
        0,
        0,
        0,
        0,
        0,
        0,
        0,
        0
    ],
    "reward_sum": 0,
    "turns": 8,
    "search count": 7,
    "script count": 0,
    "summary count": 0,
    "context lengths": [
        763,
        1755,
        2836,
        3953,
        5141,
        5890,
        6617,
        7329
    ]
}