{
    "answer": "The investor relations reports section, under the Cloudberry Clean Energy ASA investor relations site. (cloudberry.no/investor-relations/reports-and-presentations)",
    "ground_truth": "Cloudberry Clean Energy ASA Periodic Financial Report Series",
    "rewards": [
        0,
        0,
        0,
        0,
        0
    ],
    "reward_sum": 0,
    "turns": 5,
    "search count": 4,
    "script count": 0,
    "summary count": 0,
    "context lengths": [
        798,
        2523,
        4016,
        5245,
        6642
    ]
}