{
    "answer": "The volatility distribution of the unemployment rate in Hong Kong prior to January 2025 is depicted in Figure 0 as an upward trend showing daily unemployment figures from January to March 2025, with a calculation of the annual raw components that gives the implied volatility.",
    "ground_truth": "candlestick ranges",
    "rewards": [
        0,
        0,
        0,
        0,
        0
    ],
    "reward_sum": 0,
    "turns": 5,
    "search count": 4,
    "script count": 0,
    "summary count": 0,
    "context lengths": [
        892,
        2171,
        3375,
        5024,
        6883
    ]
}