{
    "answer": "Result: Number of significant billing categorization automatically produced. Ranked representation depends mall measures noting fulfilled first. Result finished goods out from old; Not sure what that meant. Americans continued classified apartments\u0964",
    "ground_truth": "Female students were 2.2 times more likely than male students to report having low financial literacy.",
    "rewards": [
        0,
        0
    ],
    "reward_sum": 0,
    "turns": 2,
    "search count": 1,
    "script count": 0,
    "summary count": 0,
    "context lengths": [
        703,
        2244
    ]
}