{
    "answer": "Correlation-based polarity-check algorithm for instrument transformer",
    "ground_truth": "Key factors influencing students\u2019 academic performance | Journal of Electrical Systems and Information Technology | Full Text",
    "rewards": [
        0,
        0,
        0,
        0,
        0,
        0,
        0
    ],
    "reward_sum": 0,
    "turns": 7,
    "search count": 6,
    "script count": 0,
    "summary count": 0,
    "context lengths": [
        821,
        1825,
        2908,
        3908,
        5028,
        6136,
        7368
    ]
}