{
    "answer": "Respondents with a high sense of grievance are less likely to exhibit a zero-sum mindset compared to those with a low sense of grievance, as sustainable development is not a zero-sum game.",
    "ground_truth": "twice as likely",
    "rewards": [
        0,
        0,
        0,
        0,
        0,
        0
    ],
    "reward_sum": 0,
    "turns": 6,
    "search count": 5,
    "script count": 0,
    "summary count": 0,
    "context lengths": [
        808,
        2063,
        3248,
        4490,
        5656,
        6995
    ]
}